flask_quill/__init__.py
flask_quill/fields.py
flask_quill-0.2.0.dist-info/METADATA
flask_quill-0.2.0.dist-info/WHEEL
flask_quill-0.2.0.dist-info/top_level.txt
flask_quill-0.2.0.dist-info/RECORD
