Metadata-Version: 2.4
Name: flask_quill
Version: 0.2.0
Summary: FlaskでQuillリッチテキストエディタを簡単に使える拡張
Home-page: 
Author: 
Author-email: 
Classifier: Programming Language :: Python :: 3
Classifier: Framework :: Flask
Classifier: License :: OSI Approved :: MIT License
Classifier: Operating System :: OS Independent
Requires-Python: >=3.7
Requires-Dist: Flask>=2.0.0
Requires-Dist: Flask-WTF>=1.0.0
Requires-Dist: WTForms>=2.3.0
Requires-Dist: bootstrap-flask>=2.0.0
Dynamic: classifier
Dynamic: description
Dynamic: description-content-type
Dynamic: requires-dist
Dynamic: requires-python
Dynamic: summary
